LICENSE
MANIFEST.in
README.rst
setup.py
docs/Makefile
docs/assumptions.rst
docs/conf.py
docs/index.rst
docs/modules.rst
docs/ocpnetsplit.rst
docs/overview_latency.rst
docs/overview_netsplit.rst
docs/usage.rst
docs/usage_multicluster.rst
docs/_build/doctrees/assumptions.doctree
docs/_build/doctrees/environment.pickle
docs/_build/doctrees/index.doctree
docs/_build/doctrees/modules.doctree
docs/_build/doctrees/ocpnetsplit.doctree
docs/_build/doctrees/overview_latency.doctree
docs/_build/doctrees/overview_netsplit.doctree
docs/_build/doctrees/usage.doctree
docs/_build/doctrees/usage_multicluster.doctree
docs/_build/html/.buildinfo
docs/_build/html/objects.inv
docs/_build/html/searchindex.js
docs/_build/html/_sources/assumptions.rst.txt
docs/_build/html/_sources/index.rst.txt
docs/_build/html/_sources/modules.rst.txt
docs/_build/html/_sources/ocpnetsplit.rst.txt
docs/_build/html/_sources/overview_latency.rst.txt
docs/_build/html/_sources/overview_netsplit.rst.txt
docs/_build/html/_sources/usage.rst.txt
docs/_build/html/_sources/usage_multicluster.rst.txt
docs/_build/html/_static/alabaster.css
docs/_build/html/_static/basic.css
docs/_build/html/_static/custom.css
docs/_build/html/_static/doctools.js
docs/_build/html/_static/documentation_options.js
docs/_build/html/_static/file.png
docs/_build/html/_static/jquery-3.5.1.js
docs/_build/html/_static/jquery.js
docs/_build/html/_static/language_data.js
docs/_build/html/_static/minus.png
docs/_build/html/_static/plus.png
docs/_build/html/_static/pygments.css
docs/_build/html/_static/searchtools.js
docs/_build/html/_static/underscore-1.13.1.js
docs/_build/html/_static/underscore-1.3.1.js
docs/_build/html/_static/underscore.js
docs/_build/linkcheck/output.json
docs/_build/linkcheck/output.txt
ocp_network_split.egg-info/PKG-INFO
ocp_network_split.egg-info/SOURCES.txt
ocp_network_split.egg-info/dependency_links.txt
ocp_network_split.egg-info/entry_points.txt
ocp_network_split.egg-info/requires.txt
ocp_network_split.egg-info/top_level.txt
ocpnetsplit/__init__.py
ocpnetsplit/machineconfig.py
ocpnetsplit/main.py
ocpnetsplit/network-latency.sh
ocpnetsplit/network-pingtest.sh
ocpnetsplit/network-split.sh
ocpnetsplit/network-zone.sh
ocpnetsplit/ocp.py
ocpnetsplit/zone.py
