Metadata-Version: 2.1
Name: ocp-network-split
Version: 0.3.0
Summary: OCP 4 platform agnostic firewall based network split tool for testing network disruptions on zone level.
Home-page: http://gitlab.com/mbukatov/ocp-network-split/
Author: Martin Bukatovič
Author-email: mbukatov@redhat.com
License: Apache License 2.0
Project-URL: Documentation, https://mbukatov.gitlab.io/ocp-network-split
Project-URL: Bug Reports, https://gitlab.com/mbukatov/ocp-network-split/-/issues
Project-URL: Source, https://gitlab.com/mbukatov/ocp-network-split/
Keywords: openshift,firewall
Platform: UNKNOWN
Classifier: License :: OSI Approved :: Apache Software License
Classifier: Topic :: Software Development :: Quality Assurance
Classifier: Topic :: System :: Networking :: Firewalls
Classifier: Topic :: System :: Clustering
Classifier: Topic :: Utilities
Classifier: Programming Language :: Python :: 3
Classifier: Programming Language :: Python :: 3 :: Only
Classifier: Programming Language :: Python :: 3.9
Classifier: Development Status :: 3 - Alpha
License-File: LICENSE
